hchacha/__init__.py
hchacha/data/GRCh37.tsv.gz
hchacha/data/GRCh38.tsv.gz
hchacha/hchacha.py
hchacha-1.0.5.dist-info/LICENSE.txt
hchacha-1.0.5.dist-info/METADATA
hchacha-1.0.5.dist-info/WHEEL
hchacha-1.0.5.dist-info/entry_points.txt
hchacha-1.0.5.dist-info/RECORD
