Metadata-Version: 2.1
Name: hchacha
Version: 1.0.5
Summary: Human CHromosome Accession CHAnge - Convert between different human chromosome naming systems (of the same assembly/version)
Home-page: https://bitbucket.org/bpow/hchacha
License: MIT
Keywords: genetics,bam,sam,vcf,variants,bed,fasta,genome,exome
Author: Bradford Powell
Author-email: bpow@drpowell.org
Requires-Python: >=3.7,<4.0
Classifier: Intended Audience :: Science/Research
Classifier: License :: OSI Approved :: MIT License
Classifier: Programming Language :: Python :: 3
Classifier: Programming Language :: Python :: 3.7
Classifier: Programming Language :: Python :: 3.8
Classifier: Programming Language :: Python :: 3.9
Classifier: Programming Language :: Python :: 3.10
Classifier: Programming Language :: Python :: 3.11
Classifier: Topic :: Scientific/Engineering :: Bio-Informatics
Project-URL: Repository, https://bitbucket.org/bpow/hchacha
